mkdocs_file_filter_plugin/__init__.py
mkdocs_file_filter_plugin/external_config.py
mkdocs_file_filter_plugin/judger.py
mkdocs_file_filter_plugin/logger.py
mkdocs_file_filter_plugin/plugin.py
mkdocs_file_filter_plugin/plugin_config.py
mkdocs_file_filter_plugin-0.2.0.dist-info/LICENSE
mkdocs_file_filter_plugin-0.2.0.dist-info/METADATA
mkdocs_file_filter_plugin-0.2.0.dist-info/WHEEL
mkdocs_file_filter_plugin-0.2.0.dist-info/entry_points.txt
mkdocs_file_filter_plugin-0.2.0.dist-info/RECORD
