Metadata-Version: 2.1
Name: mkdocs-file-filter-plugin
Version: 0.2.0
Summary: A MkDocs plugin that lets you exclude/include docs files using globs, regexes, gitignore-style file and Markdown/Frontmatter tags metadata.
Home-page: https://github.com/DariuszPorowski/mkdocs-file-filter-plugin
License: MIT
Keywords: mkdocs,plugin,exclude,include,glob,regex,gitignore,markdown,frontmatter,metadata,tags
Author: Dariusz Porowski
Author-email: 3431813+dariuszporowski@users.noreply.github.com
Requires-Python: >=3.9,<4.0
Classifier: Development Status :: 3 - Alpha
Classifier: Intended Audience :: Developers
Classifier: Intended Audience :: Information Technology
Classifier: License :: OSI Approved :: MIT License
Classifier: Operating System :: OS Independent
Classifier: Programming Language :: Python
Classifier: Programming Language :: Python :: 3
Classifier: Programming Language :: Python :: 3.9
Classifier: Programming Language :: Python :: 3.10
Classifier: Programming Language :: Python :: 3.11
Classifier: Programming Language :: Python :: 3.12
Classifier: Programming Language :: Python :: 3 :: Only
Classifier: Topic :: Documentation
Requires-Dist: igittigitt (>=2.1.4,<3.0.0)
Requires-Dist: mkdocs (>=1.5.3,<2.0.0)
Requires-Dist: pyyaml (>=6.0.1,<7.0.0)
Requires-Dist: pyyaml-env-tag (>=0.1,<0.2)
Requires-Dist: schema (>=0.7.5,<0.8.0)
Project-URL: Documentation, https://github.com/DariuszPorowski/mkdocs-file-filter-plugin/blob/main/README.md
Project-URL: History, https://github.com/DariuszPorowski/mkdocs-file-filter-plugin/releases
Project-URL: Issues, https://github.com/DariuszPorowski/mkdocs-file-filter-plugin/issues
Project-URL: Repository, https://github.com/DariuszPorowski/mkdocs-file-filter-plugin
